pelage/__init__.py
pelage/types.py
pelage/utils.py
pelage/checks/__init__.py
pelage/checks/accepted_range.py
pelage/checks/accepted_values.py
pelage/checks/at_least_one.py
pelage/checks/column_is_within_n_std.py
pelage/checks/custom_check.py
pelage/checks/has_columns.py
pelage/checks/has_dtypes.py
pelage/checks/has_mandatory_values.py
pelage/checks/has_no_infs.py
pelage/checks/has_no_nulls.py
pelage/checks/has_shape.py
pelage/checks/is_monotonic.py
pelage/checks/maintains_relationships.py
pelage/checks/mutually_exclusive_ranges.py
pelage/checks/not_accepted_values.py
pelage/checks/not_constant.py
pelage/checks/not_null_proportion.py
pelage/checks/unique.py
pelage/checks/unique_combination_of_columns.py
pelage-0.5.1.dist-info/METADATA
pelage-0.5.1.dist-info/WHEEL
pelage-0.5.1.dist-info/licenses/LICENSE
pelage-0.5.1.dist-info/RECORD
