Metadata-Version: 2.4
Name: pelage
Version: 0.5.1
Summary: This package contains a collection of tests to improve your Polars data analysis superpowers
Project-URL: homepage, https://alixtc.github.io/pelage
Project-URL: repository, https://github.com/alixtc/pelage/
Project-URL: documentation, https://alixtc.github.io/pelage/notebooks/examples.html
Author-email: Alix Tiran-Cappello <alix.tiran-cappello@laposte.net>
License: MIT
License-File: LICENSE
Requires-Python: >=3.8
Requires-Dist: polars>=0.19
